graph_writer.py
graph_writer-0.1.1.dist-info/LICENSE
graph_writer-0.1.1.dist-info/METADATA
graph_writer-0.1.1.dist-info/WHEEL
graph_writer-0.1.1.dist-info/top_level.txt
graph_writer-0.1.1.dist-info/RECORD
